{"currentVersion":11.3,"cimVersion":"3.3.0","serviceDescription":"","mapName":"Mapa","description":"","copyrightText":"","supportsDynamicLayers":true,"layers":[{"id":9,"name":"Antiguos Espacios Territoriales de Capacitación y Reincororación AETCR","parentLayerId":-1,"defaultVisibility":true,"subLayerIds":null,"minScale":0,"maxScale":0,"type":"Feature Layer","geometryType":"esriGeometryPoint","supportsDynamicLegends":true},{"id":0,"name":"Afectaciones Firmantes 1er semestre 2025","parentLayerId":-1,"defaultVisibility":true,"subLayerIds":null,"minScale":0,"maxScale":0,"type":"Feature Layer","geometryType":"esriGeometryPolygon","supportsDynamicLegends":false},{"id":23,"name":"Área de influencia GAO, GAO-r y GDCO","parentLayerId":-1,"defaultVisibility":true,"subLayerIds":[24,11,12,13,15,16],"minScale":0,"maxScale":0,"type":"Group Layer","supportsDynamicLegends":false},{"id":24,"name":"Disidencias EMBF","parentLayerId":23,"defaultVisibility":true,"subLayerIds":null,"minScale":0,"maxScale":0,"type":"Feature Layer","geometryType":"esriGeometryPolygon","supportsDynamicLegends":true},{"id":11,"name":"Antigua Segunda Marquetalia","parentLayerId":23,"defaultVisibility":true,"subLayerIds":null,"minScale":0,"maxScale":0,"type":"Feature Layer","geometryType":"esriGeometryPolygon","supportsDynamicLegends":true},{"id":12,"name":"ELN","parentLayerId":23,"defaultVisibility":true,"subLayerIds":null,"minScale":0,"maxScale":0,"type":"Feature Layer","geometryType":"esriGeometryPolygon","supportsDynamicLegends":true},{"id":13,"name":"Disidencias EMC","parentLayerId":23,"defaultVisibility":true,"subLayerIds":null,"minScale":0,"maxScale":0,"type":"Feature Layer","geometryType":"esriGeometryPolygon","supportsDynamicLegends":true},{"id":15,"name":"Clan del Golfo o AGC","parentLayerId":23,"defaultVisibility":true,"subLayerIds":null,"minScale":0,"maxScale":0,"type":"Feature Layer","geometryType":"esriGeometryPolygon","supportsDynamicLegends":true},{"id":16,"name":"ASCN","parentLayerId":23,"defaultVisibility":true,"subLayerIds":null,"minScale":0,"maxScale":0,"type":"Feature Layer","geometryType":"esriGeometryPolygon","supportsDynamicLegends":true},{"id":10,"name":"Firmantes mayo 2025","parentLayerId":-1,"defaultVisibility":true,"subLayerIds":null,"minScale":0,"maxScale":0,"type":"Feature Layer","geometryType":"esriGeometryPolygon","supportsDynamicLegends":true}],"tables":[],"spatialReference":{"wkid":102100,"latestWkid":3857,"xyTolerance":0.001,"zTolerance":0.001,"mTolerance":0.001,"falseX":-20037700,"falseY":-30241100,"xyUnits":10000,"falseZ":-100000,"zUnits":10000,"falseM":-100000,"mUnits":10000},"singleFusedMapCache":false,"initialExtent":{"xmin":-9365243.945379445,"ymin":152936.02418072266,"xmax":-7060795.5140485,"ymax":1037876.2558473407,"spatialReference":{"wkid":102100,"latestWkid":3857,"xyTolerance":0.001,"zTolerance":0.001,"mTolerance":0.001,"falseX":-20037700,"falseY":-30241100,"xyUnits":10000,"falseZ":-100000,"zUnits":10000,"falseM":-100000,"mUnits":10000}},"fullExtent":{"xmin":-9098767.65996614,"ymin":-471243.5332191968,"xmax":-7320364.57004672,"ymax":1504865.2504486765,"spatialReference":{"wkid":102100,"latestWkid":3857,"xyTolerance":0.001,"zTolerance":0.001,"mTolerance":0.001,"falseX":-20037700,"falseY":-30241100,"xyUnits":10000,"falseZ":-100000,"zUnits":10000,"falseM":-100000,"mUnits":10000}},"datesInUnknownTimezone":false,"minScale":0,"maxScale":0,"units":"esriMeters","supportedImageFormatTypes":"PNG32,PNG24,PNG,JPG,DIB,TIFF,EMF,PS,PDF,GIF,SVG,SVGZ,BMP","documentInfo":{"Title":"Mapa","Author":"","Comments":"","Subject":"","Category":"","Version":"3.4.0","AntialiasingMode":"Fast","TextAntialiasingMode":"Force","Keywords":"TIERRAS,CNR"},"supportsQueryDomains":true,"capabilities":"Map,Query,Data","supportedQueryFormats":"JSON, geoJSON, PBF","exportTilesAllowed":false,"referenceScale":0.0,"datumTransformations":[{"geoTransforms":[{"wkid":15738,"latestWkid":15738,"transformForward":false,"name":"MAGNA_To_WGS_1984_1"}]},{"geoTransforms":[{"wkid":15738,"latestWkid":15738,"transformForward":true,"name":"MAGNA_To_WGS_1984_1"}]}],"supportsDatumTransformation":true,"floorAwareMapProperties":{"defaultFloorFilterSettings":{"isEnabled":false}},"archivingInfo":{"supportsHistoricMoment":false},"supportsClipping":true,"supportsSpatialFilter":true,"supportsTimeRelation":true,"supportsQueryDataElements":true,"mapUnits":{"uwkid":9001},"maxRecordCount":2000,"maxImageHeight":4096,"maxImageWidth":4096,"supportedExtensions":"","serviceItemId":"bd155e5528bd4073adedab78dbd93ec6"}