{"currentVersion":11.3,"cimVersion":"3.3.0","serviceDescription":"","mapName":"Map50","description":"","copyrightText":"","supportsDynamicLayers":true,"layers":[{"id":0,"name":"Municipio_Victimas","parentLayerId":-1,"defaultVisibility":true,"subLayerIds":null,"minScale":0,"maxScale":0,"type":"Feature Layer","geometryType":"esriGeometryPolygon","supportsDynamicLegends":true}],"tables":[],"spatialReference":{"wkid":4326,"latestWkid":4326,"xyTolerance":8.983152841195215E-9,"zTolerance":0.001,"mTolerance":0.001,"falseX":-400,"falseY":-400,"xyUnits":9.999999999999999E8,"falseZ":-100000,"zUnits":10000,"falseM":-100000,"mUnits":10000},"singleFusedMapCache":false,"initialExtent":{"xmin":-87.42456706319304,"ymin":-5.247025737902115,"xmax":-53.03214220192574,"ymax":13.46867960147287,"spatialReference":{"wkid":4326,"latestWkid":4326,"xyTolerance":8.983152841195215E-9,"zTolerance":0.001,"mTolerance":0.001,"falseX":-400,"falseY":-400,"xyUnits":9.999999999999999E8,"falseZ":-100000,"zUnits":10000,"falseM":-100000,"mUnits":10000}},"fullExtent":{"xmin":-81.73562054499996,"ymin":-4.225935766999953,"xmax":-66.84721539899994,"ymax":13.39472776100007,"spatialReference":{"wkid":4326,"latestWkid":4326,"xyTolerance":8.983152841195215E-9,"zTolerance":0.001,"mTolerance":0.001,"falseX":-400,"falseY":-400,"xyUnits":9.999999999999999E8,"falseZ":-100000,"zUnits":10000,"falseM":-100000,"mUnits":10000}},"datesInUnknownTimezone":false,"minScale":0,"maxScale":0,"units":"esriDecimalDegrees","supportedImageFormatTypes":"PNG32,PNG24,PNG,JPG,DIB,TIFF,EMF,PS,PDF,GIF,SVG,SVGZ,BMP","documentInfo":{"Title":"Map50","Author":"","Comments":"","Subject":"","Category":"","Version":"2.7.0","AntialiasingMode":"Fast","TextAntialiasingMode":"Force","Keywords":"PruebaDash"},"supportsQueryDomains":true,"capabilities":"Query,Map,Data","supportedQueryFormats":"JSON, geoJSON, PBF","exportTilesAllowed":false,"referenceScale":0.0,"supportsDatumTransformation":true,"archivingInfo":{"supportsHistoricMoment":false},"supportsClipping":true,"supportsSpatialFilter":true,"supportsTimeRelation":true,"supportsQueryDataElements":true,"mapUnits":{"uwkid":9102},"maxRecordCount":2000,"maxImageHeight":4096,"maxImageWidth":4096,"supportedExtensions":"FeatureServer","serviceItemId":"07c69577ecf4431b997679265794deeb"}